[
    {"time":1,"data": 1.1632},
    {"time":2,"data": 1.1554},
    {"time":3,"data": 1.1593},
    {"time":4,"data": 1.1554},
    {"time":5,"data": 1.1613},
    {"time":6,"data": 1.1535},
    {"time":7,"data": 1.1554},
    {"time":8,"data": 1.1613},
    {"time":9,"data": 1.1574},
    {"time":10,"data": 1.1593},
    {"time":11,"data": 1.1574},
    {"time":12,"data": 1.1535},
    {"time":13,"data": 1.1515},
    {"time":14,"data": 1.1613},
    {"time":15,"data": 1.1515},
    {"time":16,"data": 1.1593},
    {"time":17,"data": 1.1554},
    {"time":18,"data": 1.1574},
    {"time":19,"data": 1.1632},
    {"time":20,"data": 1.1593},
    {"time":21,"data": 1.1515},
    {"time":22,"data": 1.1691},
    {"time":23,"data": 1.1613},
    {"time":24,"data": 1.1554},
    {"time":25,"data": 1.1593},
    {"time":26,"data": 1.1632},
    {"time":27,"data": 1.1574},
    {"time":28,"data": 1.1593},
    {"time":29,"data": 1.1613},
    {"time":30,"data": 1.1574},
    {"time":31,"data": 1.1476},
    {"time":32,"data": 1.1613}
]
